airtable_pg_sync/__init__.py
airtable_pg_sync/cli.py
airtable_pg_sync/logging.conf
airtable_pg_sync/sync.py
airtable_pg_sync/core/__init__.py
airtable_pg_sync/core/change_handler.py
airtable_pg_sync/core/env.py
airtable_pg_sync/core/clients/__init__.py
airtable_pg_sync/core/clients/airtable.py
airtable_pg_sync/core/clients/postgres.py
airtable_pg_sync/core/clients/response_parser.py
airtable_pg_sync/core/types/__init__.py
airtable_pg_sync/core/types/bridges.py
airtable_pg_sync/core/types/changes.py
airtable_pg_sync/core/types/concepts.py
airtable_pg_sync/core/types/env_types.py
airtable_pg_sync/initial_sync/__init__.py
airtable_pg_sync/initial_sync/individual_view_syncer.py
airtable_pg_sync/initial_sync/initial_syncer.py
airtable_pg_sync/initial_sync/reduced_memory_usage_row_syncer.py
airtable_pg_sync/initial_sync/row_syncer.py
airtable_pg_sync/initial_sync/schema_syncer.py
airtable_pg_sync/initial_sync/table_syncer.py
airtable_pg_sync/initial_sync/view_syncer.py
airtable_pg_sync/perpetual_sync/__init__.py
airtable_pg_sync/perpetual_sync/perpetual_syncer.py
airtable_pg_sync/perpetual_sync/webhook_listener.py
airtable_pg_sync-0.0.47.dist-info/LICENSE
airtable_pg_sync-0.0.47.dist-info/METADATA
airtable_pg_sync-0.0.47.dist-info/WHEEL
airtable_pg_sync-0.0.47.dist-info/entry_points.txt
airtable_pg_sync-0.0.47.dist-info/top_level.txt
airtable_pg_sync-0.0.47.dist-info/RECORD
