Metadata-Version: 2.1
Name: airtable_pg_sync
Version: 0.0.47
Summary: Sync Airtable bases to a Postgres schemas in real time
Author-email: Benjamin Urwin <benurwin@outlook.com>
License: Copyright 2023 Benjamin Urwin
Project-URL: Homepage, https://github.com/benurwin/airtable_pg_sync
Keywords: airtable,postgres,sync,realtime,webhook
Classifier: License :: OSI Approved :: MIT License
Classifier: Programming Language :: Python
Classifier: Programming Language :: Python :: 3
Requires-Python: >=3.9
License-File: LICENSE
Requires-Dist: requests
Requires-Dist: psycopg[binary]
Requires-Dist: aiohttp
Requires-Dist: click
Requires-Dist: pyyaml
Requires-Dist: rich
Requires-Dist: python-dateutil
